setup.cfg
setup.py
dnschain/__init__.py
dnschain/log.py
dnschain/server.py
dnschain.egg-info/PKG-INFO
dnschain.egg-info/SOURCES.txt
dnschain.egg-info/dependency_links.txt
dnschain.egg-info/top_level.txt
dnschain/test/__init__.py
dnschain/test/test_server.py