Metadata-Version: 1.1
Name: dnschain
Version: 0.1.0
Summary: Python library to perform DNSChain lookups
Home-page: https://github.com/okturtles/pydnschain
Author: okTurtles Foundation
Author-email: hi@okturtles.com
License: MPL 2.0
Platform: UNKNOWN
Classifier: Development Status :: 2 - Pre-Alpha
Classifier: Operating System :: Unix
Classifier: Operating System :: Microsoft :: Windows
Classifier: Environment :: MacOS X
Classifier: Programming Language :: Python
Classifier: Programming Language :: Python :: 2.7
Classifier: Programming Language :: Python :: 3
Classifier: Topic :: Security :: Cryptography
Classifier: License :: OSI Approved :: Mozilla Public License 2.0 (MPL 2.0)
